{
  "reference": "Ezekiel.36",
  "verses_data": [
    {
      "reference": "Ezekiel 36:1",
      "book": "Ezekiel",
      "chapter": 36,
      "verse": 1,
      "hebrew": "וְאַתָּ֣ה בֶן־אָדָ֔ם הִנָּבֵ֖א אֶל־הָרֵ֣י יִשְׂרָאֵ֑ל וְאָ֣מַרְתָּ֔ הָרֵי֙ יִשְׂרָאֵ֔ל שִׁמְע֖וּ דְּבַר־יְהֹוָֽה",
      "english": "And you, O mortal, prophesy to the mountains of Israel and say: O mountains of Israel, hear the word of GOD:",
      "word_count": 10
    },
    {
      "reference": "Ezekiel 36:2",
      "book": "Ezekiel",
      "chapter": 36,
      "verse": 2,
      "hebrew": "כֹּ֤ה אָמַר֙ אֲדֹנָ֣י יֱהֹוִ֔ה יַ֣עַן אָמַ֧ר הָאוֹיֵ֛ב עֲלֵיכֶ֖ם הֶאָ֑ח וּבָמ֣וֹת עוֹלָ֔ם לְמוֹרָשָׁ֖ה הָ֥יְתָה לָּֽנוּ",
      "english": "Thus said the Sovereign GOD: Because the enemy gloated over you, “Aha! Those ancient heights have become our possession!”",
      "word_count": 14
    },
    {
      "reference": "Ezekiel 36:3",
      "book": "Ezekiel",
      "chapter": 36,
      "verse": 3,
      "hebrew": "לָכֵן֙ הִנָּבֵ֣א וְאָמַרְתָּ֔ כֹּ֥ה אָמַ֖ר אֲדֹנָ֣י יֱהֹוִ֑ה יַ֣עַן בְּיַ֡עַן שַׁמּוֹת֩ וְשָׁאֹ֨ף אֶתְכֶ֜ם מִסָּבִ֗יב לִֽהְיֽוֹתְכֶ֤ם מֽוֹרָשָׁה֙ לִשְׁאֵרִ֣ית הַגּוֹיִ֔ם וַתֵּ֥עֲל֛וּ עַל־שְׂפַ֥ת לָשׁ֖וֹן וְדִבַּת־עָֽם",
      "english": "therefore prophesy, and say: Thus said the Sovereign GOD: Just because they eagerly lusted to see you become a possession of the other nations round about, so that you have become the butt of gossip in every language and of the jibes from every people—",
      "word_count": 21
    },
    {
      "reference": "Ezekiel 36:4",
      "book": "Ezekiel",
      "chapter": 36,
      "verse": 4,
      "hebrew": "לָכֵן֙ הָרֵ֣י יִשְׂרָאֵ֔ל שִׁמְע֖וּ דְּבַר־אֲדֹנָ֣י יֱהֹוִ֑ה כֹּה־אָמַ֣ר אֲדֹנָ֣י יֱ֠הֹוִ֠ה לֶהָרִ֨ים וְלַגְּבָע֜וֹת לָאֲפִיקִ֣ים וְלַגֵּאָי֗וֹת וְלֶחֳרָב֤וֹת הַשֹּֽׁמְמוֹת֙ וְלֶעָרִ֣ים הַנֶּעֱזָב֔וֹת אֲשֶׁ֨ר הָי֤וּ לְבַז֙ וּלְלַ֔עַג לִשְׁאֵרִ֥ית הַגּוֹיִ֖ם אֲשֶׁ֥ר מִסָּבִֽיב",
      "english": "truly, you mountains of Israel, hear the word of the Sovereign GOD: Thus said the Sovereign GOD to the mountains and the hills, to the watercourses and the valleys, and to the desolate wastes and deserted cities that have become a prey and a laughingstock to the other nations round about:",
      "word_count": 25
    },
    {
      "reference": "Ezekiel 36:5",
      "book": "Ezekiel",
      "chapter": 36,
      "verse": 5,
      "hebrew": "לָכֵ֗ן כֹּה־אָמַר֮ אֲדֹנָ֣י יֱהֹוִה֒ אִם־לֹ֠א בְּאֵ֨שׁ קִנְאָתִ֥י דִבַּ֛רְתִּי עַל־שְׁאֵרִ֥ית הַגּוֹיִ֖ם וְעַל־אֱד֣וֹם כֻּלָּ֑א אֲשֶׁ֣ר נָתְנֽוּ־אֶת־אַרְצִ֣י&thinsp;׀&thinsp;לָ֠הֶ֠ם לְמ֨וֹרָשָׁ֜ה בְּשִׂמְחַ֤ת כׇּל־לֵבָב֙ בִּשְׁאָ֣ט נֶ֔פֶשׁ לְמַ֥עַן מִגְרָשָׁ֖הּ לָבַֽז",
      "english": "Assuredly, thus said the Sovereign GOD: I have indeed spoken in My blazing wrath against the other nations and against all of Edom that, with wholehearted glee and with contempt, have made My land a possession for themselves for pasture and for prey.",
      "word_count": 22
    },
    {
      "reference": "Ezekiel 36:6",
      "book": "Ezekiel",
      "chapter": 36,
      "verse": 6,
      "hebrew": "לָכֵ֕ן הִנָּבֵ֖א עַל־אַדְמַ֣ת יִשְׂרָאֵ֑ל וְאָמַרְתָּ֡ לֶהָרִ֣ים וְ֠לַגְּבָע֠וֹת לָאֲפִיקִ֨ים וְלַגֵּאָי֜וֹת כֹּה־אָמַ֣ר&thinsp;׀ אֲדֹנָ֣י יֱהֹוִ֗ה הִנְנִ֨י בְקִנְאָתִ֤י וּבַֽחֲמָתִי֙ דִּבַּ֔רְתִּי יַ֛עַן כְּלִמַּ֥ת גּוֹיִ֖ם נְשָׂאתֶֽם",
      "english": "Yes, prophesy about the land of Israel, and say to the mountains and the hills, to the watercourses and to the valleys, Thus said the Sovereign GOD: Behold, I declare in My blazing wrath: Because you have suffered the taunting of the nations,",
      "word_count": 20
    },
    {
      "reference": "Ezekiel 36:7",
      "book": "Ezekiel",
      "chapter": 36,
      "verse": 7,
      "hebrew": "לָכֵ֗ן כֹּ֤ה אָמַר֙ אֲדֹנָ֣י יֱהֹוִ֔ה אֲנִ֖י נָשָׂ֣אתִי אֶת־יָדִ֑י אִם־לֹ֤א הַגּוֹיִם֙ אֲשֶׁ֣ר לָכֶ֣ם מִסָּבִ֔יב הֵ֖מָּה כְּלִמָּתָ֥ם יִשָּֽׂאוּ",
      "english": "thus said the Sovereign GOD: I hereby swear that the nations that surround you shall, in their turn, suffer disgrace.",
      "word_count": 16
    },
    {
      "reference": "Ezekiel 36:8",
      "book": "Ezekiel",
      "chapter": 36,
      "verse": 8,
      "hebrew": "וְאַתֶּ֞ם הָרֵ֤י יִשְׂרָאֵל֙ עַנְפְּכֶ֣ם תִּתֵּ֔נוּ וּפֶרְיְכֶ֥ם תִּשְׂא֖וּ לְעַמִּ֣י יִשְׂרָאֵ֑ל כִּ֥י קֵרְב֖וּ לָבֽוֹא",
      "english": "But you, O mountains of Israel, shall yield your produce and bear your fruit for My people Israel, for their return is near.",
      "word_count": 12
    },
    {
      "reference": "Ezekiel 36:9",
      "book": "Ezekiel",
      "chapter": 36,
      "verse": 9,
      "hebrew": "כִּ֖י הִנְנִ֣י אֲלֵיכֶ֑ם וּפָנִ֣יתִי אֲלֵיכֶ֔ם וְנֶעֱבַדְתֶּ֖ם וְנִזְרַעְתֶּֽם",
      "english": "For I will care for you: I will turn to you, and you shall be tilled and sown.",
      "word_count": 7
    },
    {
      "reference": "Ezekiel 36:10",
      "book": "Ezekiel",
      "chapter": 36,
      "verse": 10,
      "hebrew": "וְהִרְבֵּיתִ֤י עֲלֵיכֶם֙ אָדָ֔ם כׇּל־בֵּ֥ית יִשְׂרָאֵ֖ל כֻּלֹּ֑ה וְנֹֽשְׁבוּ֙ הֶעָרִ֔ים וְהֶחֳרָב֖וֹת תִּבָּנֶֽינָה",
      "english": "I will settle a large population on you, the whole House of Israel; the towns shall be resettled, and the ruined sites rebuilt.",
      "word_count": 10
    },
    {
      "reference": "Ezekiel 36:11",
      "book": "Ezekiel",
      "chapter": 36,
      "verse": 11,
      "hebrew": "וְהִרְבֵּיתִ֧י עֲלֵיכֶ֛ם אָדָ֥ם וּבְהֵמָ֖ה וְרָב֣וּ וּפָר֑וּ וְהוֹשַׁבְתִּ֨י אֶתְכֶ֜ם כְּקַדְמֽוֹתֵיכֶ֗ם וְהֵיטִֽבֹתִי֙ מֵרִאשֹׁ֣תֵיכֶ֔ם וִידַעְתֶּ֖ם כִּֽי־אֲנִ֥י יְהֹוָֽה",
      "english": "I will multiply human and animal upon you, and they shall increase and be fertile, and I will resettle you as you were formerly, and will make you more prosperous than you were at first. And you shall know that I am GOD.",
      "word_count": 14
    },
    {
      "reference": "Ezekiel 36:12",
      "book": "Ezekiel",
      "chapter": 36,
      "verse": 12,
      "hebrew": "וְהוֹלַכְתִּי֩ עֲלֵיכֶ֨ם אָדָ֜ם אֶת־עַמִּ֤י יִשְׂרָאֵל֙ וִירֵשׁ֔וּךָ וְהָיִ֥יתָ לָהֶ֖ם לְנַחֲלָ֑ה וְלֹא־תוֹסִ֥ף ע֖וֹד לְשַׁכְּלָֽם&nbsp;{ס}&nbsp;&nbsp;&nbsp;&nbsp;&nbsp;&nbsp;&nbsp;&nbsp;",
      "english": "I will lead a multitude—My people Israel—to you, and they shall possess you. You shall be their heritage, and you shall not again cause them to be bereaved.",
      "word_count": 12
    },
    {
      "reference": "Ezekiel 36:13",
      "book": "Ezekiel",
      "chapter": 36,
      "verse": 13,
      "hebrew": "כֹּ֤ה אָמַר֙ אֲדֹנָ֣י יֱהֹוִ֔ה יַ֚עַן אֹמְרִ֣ים לָכֶ֔ם אֹכֶ֥לֶת אָדָ֖ם (אתי) [אָ֑תְּ] וּמְשַׁכֶּ֥לֶת (גויך) [גּוֹיַ֖יִךְ] הָיִֽית",
      "english": "Thus said the Sovereign GOD: Because they say to you, “You are [a land] that devours humans, you have been a bereaver of your nations,”",
      "word_count": 15
    },
    {
      "reference": "Ezekiel 36:14",
      "book": "Ezekiel",
      "chapter": 36,
      "verse": 14,
      "hebrew": "לָכֵ֗ן אָדָם֙ לֹא־תֹ֣אכְלִי ע֔וֹד (וגויך) [וְגוֹיַ֖יִךְ] לֹ֣א (תכשלי) [תְשַׁכְּלִי־]ע֑וֹד נְאֻ֖ם אֲדֹנָ֥י יֱהֹוִֽה",
      "english": "assuredly, you shall devour humans no more, you shall never again bereave your nations—declares the Sovereign GOD.",
      "word_count": 12
    },
    {
      "reference": "Ezekiel 36:15",
      "book": "Ezekiel",
      "chapter": 36,
      "verse": 15,
      "hebrew": "וְלֹא־אַשְׁמִ֨יעַ אֵלַ֤יִךְ עוֹד֙ כְּלִמַּ֣ת הַגּוֹיִ֔ם וְחֶרְפַּ֥ת עַמִּ֖ים לֹ֣א תִשְׂאִי־ע֑וֹד (וגויך) [וְגוֹיַ֙יִךְ֙] לֹא־תַכְשִׁ֣לִי ע֔וֹד נְאֻ֖ם אֲדֹנָ֥י יֱהֹוִֽה&nbsp;{פ}",
      "english": "No more will I allow the jibes of the nations to be heard against you, no longer shall you suffer the taunting of the peoples; and never again shall you cause your nations to stumble—declares the Sovereign GOD.",
      "word_count": 16
    },
    {
      "reference": "Ezekiel 36:16",
      "book": "Ezekiel",
      "chapter": 36,
      "verse": 16,
      "hebrew": "וַיְהִ֥י דְבַר־יְהֹוָ֖ה אֵלַ֥י לֵאמֹֽר",
      "english": "The word of GOD came to me:",
      "word_count": 4
    },
    {
      "reference": "Ezekiel 36:17",
      "book": "Ezekiel",
      "chapter": 36,
      "verse": 17,
      "hebrew": "בֶּן־אָדָ֗ם בֵּ֤ית יִשְׂרָאֵל֙ יֹשְׁבִ֣ים עַל־אַדְמָתָ֔ם וַיְטַמְּא֣וּ אוֹתָ֔הּ בְּדַרְכָּ֖ם וּבַעֲלִֽילוֹתָ֑ם כְּטֻמְאַת֙ הַנִּדָּ֔ה הָיְתָ֥ה דַרְכָּ֖ם לְפָנָֽי",
      "english": "O mortal, when the House of Israel dwelt on their own soil, they defiled it with their ways and their deeds; their ways were in My sight like the impurity of a menstruous woman.",
      "word_count": 14
    },
    {
      "reference": "Ezekiel 36:18",
      "book": "Ezekiel",
      "chapter": 36,
      "verse": 18,
      "hebrew": "וָאֶשְׁפֹּ֤ךְ חֲמָתִי֙ עֲלֵיהֶ֔ם עַל־הַדָּ֖ם אֲשֶׁר־שָׁפְכ֣וּ עַל־הָאָ֑רֶץ וּבְגִלּוּלֵיהֶ֖ם טִמְּאֽוּהָ",
      "english": "So I poured out My wrath on them for the blood that they shed upon their land, and for the fetishes with which they defiled it.",
      "word_count": 8
    },
    {
      "reference": "Ezekiel 36:19",
      "book": "Ezekiel",
      "chapter": 36,
      "verse": 19,
      "hebrew": "וָאָפִ֤יץ אֹתָם֙ בַּגּוֹיִ֔ם וַיִּזָּר֖וּ בָּאֲרָצ֑וֹת כְּדַרְכָּ֥ם וְכַעֲלִילוֹתָ֖ם שְׁפַטְתִּֽים",
      "english": "I scattered them among the nations, and they were dispersed through the countries: I punished them in accordance with their ways and their deeds.",
      "word_count": 8
    },
    {
      "reference": "Ezekiel 36:20",
      "book": "Ezekiel",
      "chapter": 36,
      "verse": 20,
      "hebrew": "וַיָּב֗וֹא אֶל־הַגּוֹיִם֙ אֲשֶׁר־בָּ֣אוּ שָׁ֔ם וַֽיְחַלְּל֖וּ אֶת־שֵׁ֣ם קׇדְשִׁ֑י בֶּאֱמֹ֤ר לָהֶם֙ עַם־יְהֹוָ֣ה אֵ֔לֶּה וּמֵאַרְצ֖וֹ יָצָֽאוּ",
      "english": "But when they came to those nations, they caused My holy name to be profaned, in that it was said of them, “These are GOD’s people, yet they had to leave their land.”",
      "word_count": 13
    },
    {
      "reference": "Ezekiel 36:21",
      "book": "Ezekiel",
      "chapter": 36,
      "verse": 21,
      "hebrew": "וָאֶחְמֹ֖ל עַל־שֵׁ֣ם קׇדְשִׁ֑י אֲשֶׁ֤ר חִלְּלֻ֙הוּ֙ בֵּ֣ית יִשְׂרָאֵ֔ל בַּגּוֹיִ֖ם אֲשֶׁר־בָּ֥אוּ שָֽׁמָּה&nbsp;{פ}",
      "english": "Therefore I am concerned for My holy name, which the House of Israel have caused to be profaned among the nations to which they have come.",
      "word_count": 10
    },
    {
      "reference": "Ezekiel 36:22",
      "book": "Ezekiel",
      "chapter": 36,
      "verse": 22,
      "hebrew": "לָכֵ֞ן אֱמֹ֣ר לְבֵֽית־יִשְׂרָאֵ֗ל כֹּ֤ה אָמַר֙ אֲדֹנָ֣י יֱהֹוִ֔ה לֹ֧א לְמַעַנְכֶ֛ם אֲנִ֥י עֹשֶׂ֖ה בֵּ֣ית יִשְׂרָאֵ֑ל כִּ֤י אִם־לְשֵׁם־קׇדְשִׁי֙ אֲשֶׁ֣ר חִלַּלְתֶּ֔ם בַּגּוֹיִ֖ם אֲשֶׁר־בָּ֥אתֶם שָֽׁם",
      "english": "Say to the House of Israel: Thus said the Sovereign GOD: Not for your sake will I act, O House of Israel, but for My holy name, which you have caused to be profaned among the nations to which you have come.",
      "word_count": 20
    },
    {
      "reference": "Ezekiel 36:23",
      "book": "Ezekiel",
      "chapter": 36,
      "verse": 23,
      "hebrew": "וְקִדַּשְׁתִּ֞י אֶת־שְׁמִ֣י הַגָּד֗וֹל הַֽמְחֻלָּל֙ בַּגּוֹיִ֔ם אֲשֶׁ֥ר חִלַּלְתֶּ֖ם בְּתוֹכָ֑ם וְיָדְע֨וּ הַגּוֹיִ֜ם כִּֽי־אֲנִ֣י יְהֹוָ֗ה נְאֻם֙ אֲדֹנָ֣י יֱהֹוִ֔ה בְּהִקָּדְשִׁ֥י בָכֶ֖ם לְעֵינֵיהֶֽם",
      "english": "I will sanctify My great name that has been profaned among the nations—among whom you have caused it to be profaned. And the nations shall know that I am GOD—declares the Sovereign GOD—when I manifest My holiness before their eyes through you.",
      "word_count": 18
    },
    {
      "reference": "Ezekiel 36:24",
      "book": "Ezekiel",
      "chapter": 36,
      "verse": 24,
      "hebrew": "וְלָקַחְתִּ֤י אֶתְכֶם֙ מִן־הַגּוֹיִ֔ם וְקִבַּצְתִּ֥י אֶתְכֶ֖ם מִכׇּל־הָאֲרָצ֑וֹת וְהֵבֵאתִ֥י אֶתְכֶ֖ם אֶל־אַדְמַתְכֶֽם",
      "english": "I will take you from among the nations and gather you from all the countries, and I will bring you back to your own land.",
      "word_count": 9
    },
    {
      "reference": "Ezekiel 36:25",
      "book": "Ezekiel",
      "chapter": 36,
      "verse": 25,
      "hebrew": "וְזָרַקְתִּ֧י עֲלֵיכֶ֛ם מַ֥יִם טְהוֹרִ֖ים וּטְהַרְתֶּ֑ם מִכֹּ֧ל טֻמְאוֹתֵיכֶ֛ם וּמִכׇּל־גִּלּ֥וּלֵיכֶ֖ם אֲטַהֵ֥ר אֶתְכֶֽם",
      "english": "I will sprinkle pure water upon you, and you shall be purified: I will purify you from all your defilement and from all your fetishes.",
      "word_count": 10
    },
    {
      "reference": "Ezekiel 36:26",
      "book": "Ezekiel",
      "chapter": 36,
      "verse": 26,
      "hebrew": "וְנָתַתִּ֤י לָכֶם֙ לֵ֣ב חָדָ֔שׁ וְר֥וּחַ חֲדָשָׁ֖ה אֶתֵּ֣ן בְּקִרְבְּכֶ֑ם וַהֲסִ֨רֹתִ֜י אֶת־לֵ֤ב הָאֶ֙בֶן֙ מִבְּשַׂרְכֶ֔ם וְנָתַתִּ֥י לָכֶ֖ם לֵ֥ב בָּשָֽׂר",
      "english": "And I will give you a new heart and put a new spirit into you: I will remove the heart of stone from your body and give you a heart of flesh;",
      "word_count": 16
    },
    {
      "reference": "Ezekiel 36:27",
      "book": "Ezekiel",
      "chapter": 36,
      "verse": 27,
      "hebrew": "וְאֶת־רוּחִ֖י אֶתֵּ֣ן בְּקִרְבְּכֶ֑ם וְעָשִׂ֗יתִי אֵ֤ת אֲשֶׁר־בְּחֻקַּי֙ תֵּלֵ֔כוּ וּמִשְׁפָּטַ֥י תִּשְׁמְר֖וּ וַעֲשִׂיתֶֽם",
      "english": "and I will put My spirit into you. Thus I will cause you to follow My laws and faithfully to observe My rules.",
      "word_count": 10
    },
    {
      "reference": "Ezekiel 36:28",
      "book": "Ezekiel",
      "chapter": 36,
      "verse": 28,
      "hebrew": "וִישַׁבְתֶּ֣ם בָּאָ֔רֶץ אֲשֶׁ֥ר נָתַ֖תִּי לַאֲבֹֽתֵיכֶ֑ם וִהְיִ֤יתֶם לִי֙ לְעָ֔ם וְאָ֣נֹכִ֔י אֶהְיֶ֥ה לָכֶ֖ם לֵאלֹהִֽים",
      "english": "Then you shall dwell in the land that I gave to your ancestors, and you shall be My people and I will be your God.",
      "word_count": 12
    },
    {
      "reference": "Ezekiel 36:29",
      "book": "Ezekiel",
      "chapter": 36,
      "verse": 29,
      "hebrew": "וְהוֹשַׁעְתִּ֣י אֶתְכֶ֔ם מִכֹּ֖ל טֻמְאֽוֹתֵיכֶ֑ם וְקָרָ֤אתִי אֶל־הַדָּגָן֙ וְהִרְבֵּיתִ֣י אֹת֔וֹ וְלֹא־אֶתֵּ֥ן עֲלֵיכֶ֖ם רָעָֽב",
      "english": "And when I have delivered you from all your impurity, I will summon the grain and make it abundant, and I will not bring famine upon you.",
      "word_count": 11
    },
    {
      "reference": "Ezekiel 36:30",
      "book": "Ezekiel",
      "chapter": 36,
      "verse": 30,
      "hebrew": "וְהִרְבֵּיתִי֙ אֶת־פְּרִ֣י הָעֵ֔ץ וּתְנוּבַ֖ת הַשָּׂדֶ֑ה לְמַ֗עַן אֲ֠שֶׁ֠ר לֹ֣א תִקְח֥וּ ע֛וֹד חֶרְפַּ֥ת רָעָ֖ב בַּגּוֹיִֽם",
      "english": "I will make the fruit of your trees and the crops of your fields abundant, so that you shall never again be humiliated before the nations because of famine.",
      "word_count": 13
    },
    {
      "reference": "Ezekiel 36:31",
      "book": "Ezekiel",
      "chapter": 36,
      "verse": 31,
      "hebrew": "וּזְכַרְתֶּם֙ אֶת־דַּרְכֵיכֶ֣ם הָרָעִ֔ים וּמַעַלְלֵיכֶ֖ם אֲשֶׁ֣ר לֹֽא־טוֹבִ֑ים וּנְקֹֽטֹתֶם֙ בִּפְנֵיכֶ֔ם עַ֚ל עֲוֺנֹ֣תֵיכֶ֔ם וְעַ֖ל תּוֹעֲבוֹתֵיכֶֽם",
      "english": "Then you shall recall your evil ways and your base conduct, and you shall loathe yourselves for your iniquities and your abhorrent practices.",
      "word_count": 12
    },
    {
      "reference": "Ezekiel 36:32",
      "book": "Ezekiel",
      "chapter": 36,
      "verse": 32,
      "hebrew": "לֹ֧א לְמַעַנְכֶ֣ם אֲנִֽי־עֹשֶׂ֗ה נְאֻם֙ אֲדֹנָ֣י יֱהֹוִ֔ה יִוָּדַ֖ע לָכֶ֑ם בּ֧וֹשׁוּ וְהִכָּֽלְמ֛וּ מִדַּרְכֵיכֶ֖ם בֵּ֥ית יִשְׂרָאֵֽל&nbsp;{ס}&nbsp;&nbsp;&nbsp;&nbsp;&nbsp;&nbsp;&nbsp;&nbsp;",
      "english": "Not for your sake will I act—declares the Sovereign GOD—take good note! Be ashamed and humiliated because of your ways, O House of Israel!",
      "word_count": 13
    },
    {
      "reference": "Ezekiel 36:33",
      "book": "Ezekiel",
      "chapter": 36,
      "verse": 33,
      "hebrew": "כֹּ֤ה אָמַר֙ אֲדֹנָ֣י יֱהֹוִ֔ה בְּיוֹם֙ טַהֲרִ֣י אֶתְכֶ֔ם מִכֹּ֖ל עֲוֺנֽוֹתֵיכֶ֑ם וְהֽוֹשַׁבְתִּי֙ אֶת־הֶ֣עָרִ֔ים וְנִבְנ֖וּ הֶחֳרָבֽוֹת",
      "english": "Thus said the Sovereign GOD: When I have purified you of all your iniquities, I will people your settlements, and the ruined places shall be rebuilt;",
      "word_count": 13
    },
    {
      "reference": "Ezekiel 36:34",
      "book": "Ezekiel",
      "chapter": 36,
      "verse": 34,
      "hebrew": "וְהָאָ֥רֶץ הַנְּשַׁמָּ֖ה תֵּעָבֵ֑ד תַּ֚חַת אֲשֶׁ֣ר הָיְתָ֣ה שְׁמָמָ֔ה לְעֵינֵ֖י כׇּל־עוֹבֵֽר",
      "english": "and the desolate land, after lying waste in the sight of every passerby, shall again be tilled.",
      "word_count": 9
    },
    {
      "reference": "Ezekiel 36:35",
      "book": "Ezekiel",
      "chapter": 36,
      "verse": 35,
      "hebrew": "וְאָמְר֗וּ הָאָ֤רֶץ הַלֵּ֙זוּ֙ הַנְּשַׁמָּ֔ה הָיְתָ֖ה כְּגַן־עֵ֑דֶן וְהֶעָרִ֧ים הֶחֳרֵב֛וֹת וְהַֽנְשַׁמּ֥וֹת וְהַנֶּהֱרָס֖וֹת בְּצוּר֥וֹת יָשָֽׁבוּ",
      "english": "And it shall be said, “That land, once desolate, has become like the garden of Eden; and the cities, once ruined, desolate, and ravaged, are now populated and fortified.”",
      "word_count": 12
    },
    {
      "reference": "Ezekiel 36:36",
      "book": "Ezekiel",
      "chapter": 36,
      "verse": 36,
      "hebrew": "וְיָדְע֣וּ הַגּוֹיִ֗ם אֲשֶׁ֣ר יִֽשָּׁאֲרוּ֮ סְבִיבֽוֹתֵיכֶם֒ כִּ֣י&thinsp;׀ אֲנִ֣י יְהֹוָ֗ה בָּנִ֙יתִי֙ הַנֶּ֣הֱרָס֔וֹת נָטַ֖עְתִּי הַנְּשַׁמָּ֑ה אֲנִ֥י יְהֹוָ֖ה דִּבַּ֥רְתִּי וְעָשִֽׂיתִי&nbsp;{ס}&nbsp;&nbsp;&nbsp;&nbsp;&nbsp;&nbsp;&nbsp;&nbsp;",
      "english": "And the nations that are left around you shall know that I, GOD, have rebuilt the ravaged places and replanted the desolate land. I, GOD, have spoken and will act.",
      "word_count": 16
    },
    {
      "reference": "Ezekiel 36:37",
      "book": "Ezekiel",
      "chapter": 36,
      "verse": 37,
      "hebrew": "כֹּ֤ה אָמַר֙ אֲדֹנָ֣י יֱהֹוִ֔ה ע֗וֹד זֹ֛את אִדָּרֵ֥שׁ לְבֵֽית־יִשְׂרָאֵ֖ל לַעֲשׂ֣וֹת לָהֶ֑ם אַרְבֶּ֥ה אֹתָ֛ם כַּצֹּ֖אן אָדָֽם",
      "english": "Thus said the Sovereign GOD: Moreover, in this I will respond to the House of Israel and act for their sake: I will multiply their people like sheep.",
      "word_count": 14
    },
    {
      "reference": "Ezekiel 36:38",
      "book": "Ezekiel",
      "chapter": 36,
      "verse": 38,
      "hebrew": "כְּצֹ֣אן קׇדָשִׁ֗ים כְּצֹ֤אן יְרוּשָׁלַ֙͏ִם֙ בְּמ֣וֹעֲדֶ֔יהָ כֵּ֤ן תִּֽהְיֶ֙ינָה֙ הֶעָרִ֣ים הֶחֳרֵב֔וֹת מְלֵא֖וֹת צֹ֣אן אָדָ֑ם וְיָדְע֖וּ כִּֽי־אֲנִ֥י יְהֹוָֽה&nbsp;{פ}",
      "english": "As Jerusalem is filled with sacrificial sheep during her festivals, so shall the ruined cities be filled with flocks of people. And they shall know that I am GOD.",
      "word_count": 15
    }
  ],
  "metadata": null,
  "cached_at": "2025-12-25T00:04:45.628463"
}