[
  {
    "verse": 1,
    "reference": "Ezekiel 23:1",
    "deliberation": "Hebrew prophetic formula 'the word of YHWH came to me' treats 'word' as an active agent that can 'come'; this is conventional personification/metonymy for divine revelation, not a literal physical arrival.",
    "instances": [
      {
        "figurative_language": "yes",
        "metaphor": "no",
        "simile": "no",
        "personification": "yes",
        "idiom": "no",
        "hyperbole": "no",
        "metonymy": "yes",
        "other": "no",
        "hebrew_text": "וַיְהִי דְבַר־יְהוָה אֵלַי",
        "english_text": "The word of GOD came to me",
        "target": [
          "Divine revelation received by the prophet",
          "Prophetic communication",
          "Theological/spiritual domain"
        ],
        "vehicle": [
          "A 'word' that travels and arrives",
          "Animated message/visitor",
          "Spatial/relational domain"
        ],
        "ground": [
          "Initiative and directedness of God’s communication toward the prophet",
          "A message approaching a recipient",
          "Communication domain"
        ],
        "posture": [
          "Stresses authority and objectivity of the revelation",
          "Elevated, formal prophetic diction",
          "Theological-legal proclamation"
        ],
        "explanation": "The abstract 'word' is personified as something that can 'come' to Ezekiel and functions as a metonymy for God’s revelatory act.",
        "confidence": 0.86
      }
    ]
  },
  {
    "verse": 2,
    "reference": "Ezekiel 23:2",
    "deliberation": "This introduces the narrative of two women. Although these women will later be identified as personifications of Samaria and Jerusalem, in this verse itself the language is straightforward narrative with no explicit figurative marker yet.",
    "instances": []
  },
  {
    "verse": 3,
    "reference": "Ezekiel 23:3",
    "deliberation": "Sexual language about whoring in Egypt is part of the chapter’s sustained allegory where sexual infidelity = idolatry/political infidelity. The detailed breast imagery elaborates the same metaphor, not a separate figure.",
    "instances": [
      {
        "figurative_language": "yes",
        "metaphor": "yes",
        "simile": "no",
        "personification": "no",
        "idiom": "no",
        "hyperbole": "no",
        "metonymy": "no",
        "other": "no",
        "hebrew_text": "וַתִּזְנֶינָה בְמִצְרַיִם בִּנְעוּרֵיהֶן זָנוּ",
        "english_text": "They played the whore in Egypt; they played the whore while still young.",
        "target": [
          "Israel/Judah’s early covenantal behavior toward Egypt",
          "Unfaithful political-religious alliances",
          "Theological-historical domain"
        ],
        "vehicle": [
          "Young women engaging in prostitution",
          "Sexual promiscuity/whoring",
          "Sexual/social domain"
        ],
        "ground": [
          "Illicit, unfaithful, shameful liaisons for gain or desire",
          "Betrayal of rightful loyalty by seeking forbidden partners",
          "Moral/relational domain"
        ],
        "posture": [
          "Sharp condemnation of their early unfaithfulness",
          "Negative prophetic evaluation of their history",
          "Judgmental/theological stance"
        ],
        "explanation": "Sexual whoring in Egypt figuratively depicts Israel’s early unfaithful dependence on Egypt and idolatry, using prostitution as a metaphor for covenantal betrayal.",
        "confidence": 0.96
      }
    ]
  },
  {
    "verse": 4,
    "reference": "Ezekiel 23:4",
    "deliberation": "This verse explicitly identifies the women with Samaria and Jerusalem, turning them into personifications. The naming itself is the key metaphor; the rest of the verse continues the narrative.",
    "instances": [
      {
        "figurative_language": "yes",
        "metaphor": "yes",
        "simile": "no",
        "personification": "yes",
        "idiom": "no",
        "hyperbole": "no",
        "metonymy": "yes",
        "other": "no",
        "hebrew_text": "וּשְׁמוֹתָן שֹׁמְרוֹן אׇהֳלָה וִירוּשָׁלַ͏ִם אׇהֳלִיבָה",
        "english_text": "As for their names, Oholah is Samaria, and Oholibah is Jerusalem.",
        "target": [
          "The cities/kingdoms of Samaria and Jerusalem",
          "Covenant communities",
          "Historical-political domain"
        ],
        "vehicle": [
          "Two sisters named Oholah and Oholibah",
          "Women/wives in a household",
          "Family/marital domain"
        ],
        "ground": [
          "Shared origin, marital status, and capacity for infidelity",
          "Cities relating to God as wives who can be faithful or unfaithful",
          "Covenant/marriage conceptual domain"
        ],
        "posture": [
          "Frames the cities as morally responsible actors",
          "Sets up a moral narrative of marital infidelity",
          "Prophetic-judicial stance"
        ],
        "explanation": "Samaria and Jerusalem are personified as two women/wives, introducing the extended metaphor of city as unfaithful spouse.",
        "confidence": 0.97
      }
    ]
  },
  {
    "verse": 5,
    "reference": "Ezekiel 23:5",
    "deliberation": "Describes Oholah whoring and lusting after Assyrian 'lovers'. Within the allegory, this sexual language is figurative for political and religious infidelity.",
    "instances": [
      {
        "figurative_language": "yes",
        "metaphor": "yes",
        "simile": "no",
        "personification": "no",
        "idiom": "no",
        "hyperbole": "no",
        "metonymy": "no",
        "other": "no",
        "hebrew_text": "וַתִּזֶן אׇהֳלָה תַּחְתָּי וַתֶּעְגַּב עַל־מְאַהֲבֶיהָ אֶל־אַשּׁוּר",
        "english_text": "Oholah whored while she was Mine, and she lusted after her lovers, after the Assyrians",
        "target": [
          "Samaria’s relationship with Assyria",
          "Unfaithful political-religious alliances",
          "Theological-political domain"
        ],
        "vehicle": [
          "A married woman who whores and lusts after lovers",
          "Adulterous prostitution",
          "Sexual/marital domain"
        ],
        "ground": [
          "Seeking illicit partners despite belonging to a rightful husband",
          "Betrayal, illicit desire, and dependence on others",
          "Moral-relational domain"
        ],
        "posture": [
          "Highlighting betrayal of exclusive loyalty to YHWH",
          "Indignant, accusatory prophetic tone",
          "Judgmental-theological stance"
        ],
        "explanation": "Samaria’s pursuit of Assyria is depicted as a married woman’s prostitution and lust for lovers, conveying covenantal unfaithfulness.",
        "confidence": 0.97
      }
    ]
  },
  {
    "verse": 6,
    "reference": "Ezekiel 23:6",
    "deliberation": "Descriptive language about Assyrian officials and cavalry; within the allegory these are the attractive 'lovers', but the verse itself only gives literal descriptors of their appearance and rank.",
    "instances": []
  },
  {
    "verse": 7,
    "reference": "Ezekiel 23:7",
    "deliberation": "Continues the prostitution imagery and explicitly connects it with idolatry ('their fetishes'). The sexual terms function metaphorically for idolatrous engagement.",
    "instances": [
      {
        "figurative_language": "yes",
        "metaphor": "yes",
        "simile": "no",
        "personification": "no",
        "idiom": "no",
        "hyperbole": "no",
        "metonymy": "no",
        "other": "no",
        "hebrew_text": "וַתִּתֵּן תַּזְנוּתֶיהָ עֲלֵיהֶם ... וּבְכֹל אֲשֶׁר־עָגְבָה בְּכָל־גִּלּוּלֵיהֶם נִטְמָאָה",
        "english_text": "She bestowed her whorings upon them... and defiled herself with all their fetishes after which she lusted.",
        "target": [
          "Samaria’s idolatrous involvement with Assyrian cults",
          "Religious-political infidelity",
          "Theological/cultic domain"
        ],
        "vehicle": [
          "A prostitute bestowing sexual favors on her chosen clients",
          "Commercialized sexual promiscuity",
          "Sexual/social domain"
        ],
        "ground": [
          "Eager, repeated, degrading engagement with forbidden partners",
          "Self-inflicted defilement for the sake of desire",
          "Moral-purity domain"
        ],
        "posture": [
          "Depicts her behavior as shameless and self-defiling",
          "Strong condemnation of syncretism",
          "Prophetic-judgment stance"
        ],
        "explanation": "Whorings bestowed on the Assyrians represent Samaria’s active, degrading participation in their idolatry.",
        "confidence": 0.95
      }
    ]
  },
  {
    "verse": 8,
    "reference": "Ezekiel 23:8",
    "deliberation": "Again uses sexual whoring to portray persistent ties to Egypt’s influence and idolatry. The graphic description extends the same metaphor.",
    "instances": [
      {
        "figurative_language": "yes",
        "metaphor": "yes",
        "simile": "no",
        "personification": "no",
        "idiom": "no",
        "hyperbole": "no",
        "metonymy": "no",
        "other": "no",
        "hebrew_text": "וְאֶת־תַּזְנוּתֶיהָ מִמִּצְרַיִם לֹא עָזָבָה ... וַיִּשְׁפְּכוּ תַזְנוּתָם עָלֶיהָ",
        "english_text": "She did not give up the whoring she had begun with the Egyptians... and had poured out their lust upon her.",
        "target": [
          "Ongoing Egypt-oriented idolatry and alliances",
          "Persistent covenantal unfaithfulness",
          "Theological-political domain"
        ],
        "vehicle": [
          "A woman continuing prostitution with earlier clients who pour out sexual emission on her",
          "Sexual exploitation and promiscuity",
          "Sexual/embodied domain"
        ],
        "ground": [
          "Refusal to break with degrading prior relationships",
          "Being used and defiled by those relationships",
          "Moral/relational domain"
        ],
        "posture": [
          "Emphasizes stubborn, degrading attachment to Egypt",
          "Indignant prophetic assessment",
          "Judgmental-theological stance"
        ],
        "explanation": "Her continued 'whoring' with Egypt metaphorically depicts Israel/Judah’s refusal to abandon Egyptian religious-political dependence.",
        "confidence": 0.96
      }
    ]
  },
  {
    "verse": 9,
    "reference": "Ezekiel 23:9",
    "deliberation": "The 'lovers' are figurative for the Assyrian powers she courted; 'into the hand' is a standard metonymic idiom for power/control.",
    "instances": [
      {
        "figurative_language": "yes",
        "metaphor": "yes",
        "simile": "no",
        "personification": "no",
        "idiom": "no",
        "hyperbole": "no",
        "metonymy": "no",
        "other": "no",
        "hebrew_text": "בְּיַד־מְאַהֲבֶיהָ ... בְּיַד בְּנֵי אַשּׁוּר אֲשֶׁר עָגְבָה עֲלֵיהֶם",
        "english_text": "into the hands of her lovers, into the hands of the Assyrians after whom she lusted.",
        "target": [
          "Foreign powers (Assyria) to whom Samaria turned",
          "Political-military patrons",
          "Geopolitical domain"
        ],
        "vehicle": [
          "Lovers of an adulterous woman",
          "Sexual partners pursued for desire",
          "Sexual/relational domain"
        ],
        "ground": [
          "Those she desired become those who dominate and harm her",
          "Misplaced trust in illicit partners",
          "Moral-relational domain"
        ],
        "posture": [
          "Highlights ironic retribution through former allies",
          "Critical prophetic stance toward such alliances",
          "Judgmental-theological posture"
        ],
        "explanation": "Assyrian allies are called her 'lovers', continuing the metaphor of political dependence as adulterous relationships.",
        "confidence": 0.95
      },
      {
        "figurative_language": "yes",
        "metaphor": "no",
        "simile": "no",
        "personification": "no",
        "idiom": "yes",
        "hyperbole": "no",
        "metonymy": "yes",
        "other": "no",
        "hebrew_text": "בְּיַד־מְאַהֲבֶיהָ",
        "english_text": "into the hands of her lovers",
        "target": [
          "Samaria’s subjection to Assyrian control",
          "Experience of being overpowered",
          "Political/military domain"
        ],
        "vehicle": [
          "Someone placed into another’s 'hand'",
          "Control or power represented by the hand",
          "Bodily/action domain"
        ],
        "ground": [
          "Hands exercise power and control",
          "Being in another’s hand equals being under their power",
          "Agency/control domain"
        ],
        "posture": [
          "Presents the domination as divinely decreed consequence",
          "Legal-judicial connotation of being handed over",
          "Theological-judicial stance"
        ],
        "explanation": "The idiom 'into the hand' uses 'hand' metonymically for power, meaning she was delivered into their control.",
        "confidence": 0.9
      }
    ]
  },
  {
    "verse": 10,
    "reference": "Ezekiel 23:10",
    "deliberation": "Uses sexual shame imagery ('exposed her nakedness') for public humiliation; 'she became a name/byword among women' is a metonymy/idiom for being an object lesson.",
    "instances": [
      {
        "figurative_language": "yes",
        "metaphor": "yes",
        "simile": "no",
        "personification": "no",
        "idiom": "no",
        "hyperbole": "no",
        "metonymy": "no",
        "other": "no",
        "hebrew_text": "הֵמָּה גִּלּוּ עֶרְוָתָהּ",
        "english_text": "They exposed her nakedness",
        "target": [
          "Samaria’s humiliation and loss of security",
          "Political/moral disgrace",
          "Socio-political domain"
        ],
        "vehicle": [
          "A woman’s nakedness being exposed",
          "Sexual shame and public stripping",
          "Sexual/social domain"
        ],
        "ground": [
          "Exposure of what should be covered brings shame",
          "Public vulnerability and dishonor",
          "Honor/shame domain"
        ],
        "posture": [
          "Portrays conquest as shaming judgment",
          "Severe prophetic indictment",
          "Judgmental-theological stance"
        ],
        "explanation": "Exposing her nakedness metaphorically depicts the shaming and total exposure of Samaria through conquest.",
        "confidence": 0.94
      },
      {
        "figurative_language": "yes",
        "metaphor": "no",
        "simile": "no",
        "personification": "no",
        "idiom": "yes",
        "hyperbole": "no",
        "metonymy": "yes",
        "other": "no",
        "hebrew_text": "וַתְּהִי־שֵׁם לַנָּשִׁים",
        "english_text": "she became a name among women",
        "target": [
          "Samaria’s reputation after judgment",
          "A cautionary example",
          "Social-communicative domain"
        ],
        "vehicle": [
          "A 'name' spoken among women",
          "Reputation/proverbial example",
          "Linguistic/social domain"
        ],
        "ground": [
          "Names signify reputation in communal speech",
          "Her fate becomes a talked-about warning",
          "Collective-memory domain"
        ],
        "posture": [
          "Presents her as a negative object lesson",
          "Didactic, warning function of the narrative",
          "Moral-exemplary stance"
        ],
        "explanation": "'Name' is used metonymically for reputation; she becomes a proverbial example among nations (women).",
        "confidence": 0.9
      }
    ]
  },
  {
    "verse": 11,
    "reference": "Ezekiel 23:11",
    "deliberation": "Continues the sexual metaphor, now applied to Oholibah, whose lust and whoring exceed her sister’s. The language is still figurative for Judah’s greater infidelity.",
    "instances": [
      {
        "figurative_language": "yes",
        "metaphor": "yes",
        "simile": "no",
        "personification": "yes",
        "idiom": "no",
        "hyperbole": "no",
        "metonymy": "no",
        "other": "no",
        "hebrew_text": "וַתַּשְׁחֵת עַגְבָתָהּ מִמֶּנָּה וְאֶת־תַּזְנוּתֶיהָ",
        "english_text": "yet her lusting was more depraved than her sister’s, and her whoring more debased.",
        "target": [
          "Jerusalem’s religious-political behavior",
          "Degree of covenantal infidelity",
          "Theological-moral domain"
        ],
        "vehicle": [
          "A sister’s excessive lust and prostitution surpassing another’s",
          "Escalating sexual depravity",
          "Sexual/relational domain"
        ],
        "ground": [
          "More extreme, shameless pursuit of forbidden partners",
          "Surpassing even bad precedent in corruption",
          "Moral-comparative domain"
        ],
        "posture": [
          "Heightens Judah’s guilt beyond Samaria’s",
          "Emphatically condemnatory tone",
          "Judgmental-theological stance"
        ],
        "explanation": "Jerusalem’s worsening idolatry and alliances are depicted as a sister whose lust and whoring are even more depraved than Samaria’s.",
        "confidence": 0.96
      }
    ]
  },
  {
    "verse": 12,
    "reference": "Ezekiel 23:12",
    "deliberation": "Reiterates lust for Assyrian officials. Within the sustained allegory, this is still sexual metaphor for political and religious desire.",
    "instances": [
      {
        "figurative_language": "yes",
        "metaphor": "yes",
        "simile": "no",
        "personification": "no",
        "idiom": "no",
        "hyperbole": "no",
        "metonymy": "no",
        "other": "no",
        "hebrew_text": "אֶל־בְּנֵי אַשּׁוּר עָגָבָה",
        "english_text": "She lusted after the Assyrians",
        "target": [
          "Jerusalem’s attraction to Assyrian power/culture",
          "Desire for foreign support and worship",
          "Political-religious domain"
        ],
        "vehicle": [
          "Sexual lust for men",
          "Erotic desire",
          "Sexual/emotional domain"
        ],
        "ground": [
          "Strong attraction drawing one to forbidden partners",
          "Emotionally charged pursuit of what is off-limits",
          "Desire/attachment domain"
        ],
        "posture": [
          "Frames political attraction as morally shameful lust",
          "Critical prophetic evaluation",
          "Judgmental stance"
        ],
        "explanation": "Her desire for Assyria is cast as erotic lust, continuing the metaphor of political-idolatrous attraction as sexual craving.",
        "confidence": 0.94
      }
    ]
  },
  {
    "verse": 13,
    "reference": "Ezekiel 23:13",
    "deliberation": "The main figure is 'way/path' used metaphorically for conduct. 'Defiled herself' draws on purity language but the key compact image is derekh as lifestyle.",
    "instances": [
      {
        "figurative_language": "yes",
        "metaphor": "yes",
        "simile": "no",
        "personification": "no",
        "idiom": "no",
        "hyperbole": "no",
        "metonymy": "no",
        "other": "no",
        "hebrew_text": "דֶּרֶךְ אֶחָד לִשְׁתֵּיהֶן",
        "english_text": "Both of them followed the same course [lit. one way was to both of them]",
        "target": [
          "Samaria’s and Jerusalem’s pattern of behavior",
          "Moral/covenantal conduct",
          "Ethical-spiritual domain"
        ],
        "vehicle": [
          "A single road or path walked by two travelers",
          "Journey/route",
          "Spatial/motion domain"
        ],
        "ground": [
          "Shared direction and destination indicate same chosen course",
          "Moral choices likened to walking a path",
          "Life-course domain"
        ],
        "posture": [
          "Presents their behavior as a deliberate chosen route",
          "Judgmental yet explanatory tone",
          "Prophetic-analytical stance"
        ],
        "explanation": "Their similar behavior is depicted as walking the same 'way', a common Hebrew metaphor for one’s manner of life.",
        "confidence": 0.93
      }
    ]
  },
  {
    "verse": 14,
    "reference": "Ezekiel 23:14",
    "deliberation": "Adds to Oholibah’s 'whorings' when she sees Chaldean images. The key figure is still the whoring metaphor for idolatrous attraction; the description of wall art is literal within the story.",
    "instances": [
      {
        "figurative_language": "yes",
        "metaphor": "yes",
        "simile": "no",
        "personification": "no",
        "idiom": "no",
        "hyperbole": "no",
        "metonymy": "no",
        "other": "no",
        "hebrew_text": "וַתּוֹסֶף אֶל־תַּזְנוּתֶיהָ",
        "english_text": "but she carried her whoring further",
        "target": [
          "Jerusalem’s increasing idolatrous and political entanglements",
          "Escalating covenant infidelity",
          "Theological-political domain"
        ],
        "vehicle": [
          "A prostitute increasing her acts of whoring",
          "Expanding sexual promiscuity",
          "Sexual/relational domain"
        ],
        "ground": [
          "More numerous/varied illicit liaisons correspond to more diverse infidelities",
          "Intensification of corrupt behavior",
          "Moral-degradation domain"
        ],
        "posture": [
          "Highlights worsening guilt beyond earlier behavior",
          "Strongly condemnatory prophetic tone",
          "Judgmental stance"
        ],
        "explanation": "Her growing idolatry and alliances are depicted as adding to her acts of prostitution.",
        "confidence": 0.94
      }
    ]
  },
  {
    "verse": 15,
    "reference": "Ezekiel 23:15",
    "deliberation": "Purely descriptive of the figures’ dress and appearance; within the allegory they are objects of desire, but this verse itself offers no additional figurative expression beyond that ongoing framework.",
    "instances": []
  },
  {
    "verse": 16,
    "reference": "Ezekiel 23:16",
    "deliberation": "Again uses the language of lust at first sight and sending messengers, which in context is figurative for political courting. The key image is lusting after the portrayed men.",
    "instances": [
      {
        "figurative_language": "yes",
        "metaphor": "yes",
        "simile": "no",
        "personification": "yes",
        "idiom": "no",
        "hyperbole": "no",
        "metonymy": "no",
        "other": "no",
        "hebrew_text": "וַתַּעְגְּבָה עֲלֵיהֶם לְמַרְאֵה עֵינֶיהָ",
        "english_text": "At the very sight of them she lusted after them",
        "target": [
          "Jerusalem’s attraction to Babylonian power and culture",
          "Desire for foreign alliances/ways",
          "Political-cultural domain"
        ],
        "vehicle": [
          "Instant sexual lust at visual stimulus",
          "Erotic attraction to seen men",
          "Sexual/emotional domain"
        ],
        "ground": [
          "Sudden, visually triggered desire for forbidden others",
          "Uncritical, impulsive attraction",
          "Psychological-desire domain"
        ],
        "posture": [
          "Depicts her as shallowly captivated and morally reckless",
          "Sarcastic, disapproving prophetic tone",
          "Judgmental stance"
        ],
        "explanation": "Her readiness to seek Babylon is cast as lust that erupts merely from seeing their images.",
        "confidence": 0.93
      }
    ]
  },
  {
    "verse": 17,
    "reference": "Ezekiel 23:17",
    "deliberation": "Continues the sexual metaphor ('lovemaking', 'whoring') for Judah-Babylon relations; 'her soul was disgusted with them' is an idiom for inner revulsion but not a separate image here.",
    "instances": [
      {
        "figurative_language": "yes",
        "metaphor": "yes",
        "simile": "no",
        "personification": "yes",
        "idiom": "no",
        "hyperbole": "no",
        "metonymy": "no",
        "other": "no",
        "hebrew_text": "וַיָּבֹאוּ אֵלֶיהָ בְּנֵי־בָבֶל לְמִשְׁכַּב דֹּדִים וַיְטַמְּאוּ אֹתָהּ בְּתַזְנוּתָם",
        "english_text": "So the Babylonians came to her for lovemaking and defiled her with their whoring",
        "target": [
          "Jerusalem’s engagement with Babylonian politics and cult",
          "Compromising foreign entanglements",
          "Theological-political domain"
        ],
        "vehicle": [
          "Sexual intercourse with many lovers that defiles a woman",
          "Adulterous lovemaking and prostitution",
          "Sexual/relational domain"
        ],
        "ground": [
          "Intimate union with morally corrupt partners brings defilement",
          "Shared guilt through intimate association",
          "Purity/contamination domain"
        ],
        "posture": [
          "Portrays her as both agent and victim of defilement",
          "Strong prophetic censure",
          "Judgmental-theological stance"
        ],
        "explanation": "Sexual union with Babylon represents Jerusalem’s intimate participation in Babylon’s idolatry and politics.",
        "confidence": 0.95
      }
    ]
  },
  {
    "verse": 18,
    "reference": "Ezekiel 23:18",
    "deliberation": "Reemphasizes sexual shamelessness ('flaunted her whoring, exposed her nakedness') and God’s disgust. This is metaphor for brazen public idolatry and moral exposure.",
    "instances": [
      {
        "figurative_language": "yes",
        "metaphor": "yes",
        "simile": "no",
        "personification": "yes",
        "idiom": "no",
        "hyperbole": "no",
        "metonymy": "no",
        "other": "no",
        "hebrew_text": "וַתְּגַל תַּזְנוּתֶיהָ וַתְּגַל אֶת־עֶרְוָתָהּ",
        "english_text": "She flaunted her whoring and exposed her nakedness",
        "target": [
          "Jerusalem’s open practice of idolatry and alliances",
          "Brazen covenant infidelity",
          "Theological-public domain"
        ],
        "vehicle": [
          "A prostitute who openly displays her sexual acts and nudity",
          "Shameless sexual exhibition",
          "Sexual/social domain"
        ],
        "ground": [
          "No attempt to hide disgraceful behavior",
          "Public display of what should be shameful",
          "Honor/shame domain"
        ],
        "posture": [
          "Accentuates the outrageous boldness of her sin",
          "Provokes divine revulsion",
          "Judgmental-theological stance"
        ],
        "explanation": "Her unrestrained idolatry and alliances are likened to a woman who brazenly displays her whoring and nakedness.",
        "confidence": 0.96
      }
    ]
  },
  {
    "verse": 19,
    "reference": "Ezekiel 23:19",
    "deliberation": "Again uses 'whored still more' for renewed Egyptian involvement. The phrase recalls and extends the same adultery metaphor for covenant unfaithfulness.",
    "instances": [
      {
        "figurative_language": "yes",
        "metaphor": "yes",
        "simile": "no",
        "personification": "yes",
        "idiom": "no",
        "hyperbole": "no",
        "metonymy": "no",
        "other": "no",
        "hebrew_text": "וַתַּרְבֶּה אֶת־תַּזְנוּתֶיהָ ... אֲשֶׁר זָנְתָה בְּאֶרֶץ מִצְרָיִם",
        "english_text": "But she whored still more, remembering how in her youth she had played the whore in the land of Egypt",
        "target": [
          "Jerusalem’s reversion to Egypt-oriented policies and cults",
          "Renewed unfaithfulness",
          "Theological-political domain"
        ],
        "vehicle": [
          "A woman increasing her prostitution by revisiting youthful whoredoms",
          "Expanded sexual promiscuity based on remembered pleasures",
          "Sexual/psychological domain"
        ],
        "ground": [
          "Nostalgic recall of earlier illicit pleasures spurring further sin",
          "Greater quantitative and qualitative corruption",
          "Moral-decline domain"
        ],
        "posture": [
          "Depicts her as willfully regressing into past sins",
          "Sharply condemnatory tone",
          "Judgmental-theological stance"
        ],
        "explanation": "Going back to Egypt is depicted as returning to the whoredoms of her youth, intensifying the adultery metaphor.",
        "confidence": 0.95
      }
    ]
  },
  {
    "verse": 20,
    "reference": "Ezekiel 23:20",
    "deliberation": "Employs explicit animal comparisons to exaggerate the virility of the lovers. These are similes embedded in the sexual metaphor and also function hyperbolically.",
    "instances": [
      {
        "figurative_language": "yes",
        "metaphor": "no",
        "simile": "yes",
        "personification": "no",
        "idiom": "no",
        "hyperbole": "yes",
        "metonymy": "no",
        "other": "no",
        "hebrew_text": "אֲשֶׁר בְּשַׂר־חֲמוֹרִים בְּשָׂרָם",
        "english_text": "whose members were like those of donkeys [lit. whose flesh is the flesh of donkeys]",
        "target": [
          "Perceived sexual potency/attractiveness of the foreign men",
          "Exaggerated virility and appeal",
          "Sexual-psychological domain"
        ],
        "vehicle": [
          "The flesh (genitals) of donkeys",
          "Large animal virility",
          "Animal/sexual domain"
        ],
        "ground": [
          "Impression of great size and strength in sexual organs",
          "Brutish, excessive sexuality",
          "Intensity/excess domain"
        ],
        "posture": [
          "Grossly caricatures what she finds attractive",
          "Scornful, mocking prophetic tone",
          "Judgmental-rhetorical stance"
        ],
        "explanation": "The men’s genitals are likened to those of donkeys, an exaggerated simile to stress her attraction to their brute virility.",
        "confidence": 0.97
      },
      {
        "figurative_language": "yes",
        "metaphor": "no",
        "simile": "yes",
        "personification": "no",
        "idiom": "no",
        "hyperbole": "yes",
        "metonymy": "no",
        "other": "no",
        "hebrew_text": "וְזִרְמַת סוּסִים זִרְמָתָם",
        "english_text": "and whose organs were like those of stallions [lit. whose emission is the emission of horses]",
        "target": [
          "The sexual emission/activity of the foreign men",
          "Excessive sexual power",
          "Sexual-energetic domain"
        ],
        "vehicle": [
          "The seminal emission of horses",
          "Stallion virility and copiousness",
          "Animal/sexual domain"
        ],
        "ground": [
          "Abundant, powerful emission signals potent sexuality",
          "Overwhelming, animal-like drive",
          "Excess/force domain"
        ],
        "posture": [
          "Intentionally shocking portrayal of her desires",
          "Ridicules and condemns her cravings",
          "Prophetic-satirical stance"
        ],
        "explanation": "The comparison to stallions’ emission hyperbolically depicts the lovers’ supposed sexual power and the extremity of her lust.",
        "confidence": 0.96
      }
    ]
  },
  {
    "verse": 21,
    "reference": "Ezekiel 23:21",
    "deliberation": "Speaks of 'revisiting the lewdness of your youth' and Egyptian men handling her breasts; the central figure remains the prostitution metaphor for returning to earlier unfaithfulness.",
    "instances": [
      {
        "figurative_language": "yes",
        "metaphor": "yes",
        "simile": "no",
        "personification": "yes",
        "idiom": "no",
        "hyperbole": "no",
        "metonymy": "no",
        "other": "no",
        "hebrew_text": "וַתִּפְקְדִי אֵת זִמַּת נְעוּרָיִךְ",
        "english_text": "Thus you reverted to the wantonness of your youth",
        "target": [
          "Judah’s return to former patterns of idolatry/alliance",
          "Repetition of youthful sins",
          "Theological-historical domain"
        ],
        "vehicle": [
          "Revisiting earlier sexual lewdness",
          "Renewed youthful promiscuity",
          "Sexual/temporal domain"
        ],
        "ground": [
          "Going back to earlier forbidden pleasures",
          "Repeating adolescent folly instead of maturing",
          "Moral-development domain"
        ],
        "posture": [
          "Critiques regression rather than repentance",
          "Mildly ironic, heavily condemnatory tone",
          "Prophetic-judgment stance"
        ],
        "explanation": "Her return to Egypt-like sins is cast as revisiting the wanton sexual behavior of her youth.",
        "confidence": 0.94
      }
    ]
  },
  {
    "verse": 22,
    "reference": "Ezekiel 23:22",
    "deliberation": "The Syrians/Babylonians are again called 'lovers'. God 'rouses' them against her; the figurative element is primarily the metaphorical lovers for hostile powers.",
    "instances": [
      {
        "figurative_language": "yes",
        "metaphor": "yes",
        "simile": "no",
        "personification": "yes",
        "idiom": "no",
        "hyperbole": "no",
        "metonymy": "no",
        "other": "no",
        "hebrew_text": "הִנְנִי מֵעִיר אֶת־מְאַהֲבַיִךְ עָלַיִךְ אֵת אֲשֶׁר־נָקְעָה נַפְשֵׁךְ מֵהֶם",
        "english_text": "I am going to rouse against you the lovers from whom you turned in disgust",
        "target": [
          "Foreign nations previously courted by Judah",
          "Former political-idolatrous partners turned enemies",
          "Geopolitical/theological domain"
        ],
        "vehicle": [
          "Lovers recalled and stirred up against an unfaithful woman",
          "Sexual partners whose relationship has soured",
          "Sexual/relational domain"
        ],
        "ground": [
          "Past intimate partners now become hostile",
          "Alliance turned into animosity",
          "Relational-retribution domain"
        ],
        "posture": [
          "Underscores ironic reversal orchestrated by God",
          "Judicial and ironic prophetic tone",
          "Theological-judgment stance"
        ],
        "explanation": "The nations she once treated as lovers are now roused by God against her, continuing the adultery metaphor with an ironic twist.",
        "confidence": 0.95
      }
    ]
  },
  {
    "verse": 23,
    "reference": "Ezekiel 23:23",
    "deliberation": "Lists specific peoples and describes them as 'handsome young fellows'; within the allegory these are appealing lovers, but the verse mainly gives literal ethnic and rank identifications.",
    "instances": []
  },
  {
    "verse": 24,
    "reference": "Ezekiel 23:24",
    "deliberation": "Describes military assault in quite concrete terms; 'I will entrust your punishment to them' is legal language but not strongly figurative in itself.",
    "instances": []
  },
  {
    "verse": 25,
    "reference": "Ezekiel 23:25",
    "deliberation": "Two key figures: God 'puts' His jealousy in her, treating jealousy as a quasi-objective force, and her 'remnant' is 'devoured by fire', personifying fire as an eater.",
    "instances": [
      {
        "figurative_language": "yes",
        "metaphor": "no",
        "simile": "no",
        "personification": "yes",
        "idiom": "no",
        "hyperbole": "no",
        "metonymy": "no",
        "other": "yes",
        "hebrew_text": "וְנָתַתִּי קִנְאָתִי בָּךְ",
        "english_text": "I will direct My passion [jealousy] against you [lit. put My jealousy in you]",
        "target": [
          "God’s zeal/jealous anger expressed in judgment",
          "Divine emotional disposition toward Judah",
          "Theological-affective domain"
        ],
        "vehicle": [
          "Jealousy as something placed inside a person",
          "An internalized, active force",
          "Psychological/force domain"
        ],
        "ground": [
          "Jealousy motivates and energizes actions",
          "Inner passion driving outward fury",
          "Emotion-causation domain"
        ],
        "posture": [
          "Frames judgment as driven by covenant jealousy",
          "Intense, passionate divine stance",
          "Theological-judicial posture"
        ],
        "explanation": "God’s jealousy is treated as a quasi-substantial force put 'in' her, personifying the emotion as an agent of destruction.",
        "confidence": 0.9
      },
      {
        "figurative_language": "yes",
        "metaphor": "yes",
        "simile": "no",
        "personification": "yes",
        "idiom": "no",
        "hyperbole": "no",
        "metonymy": "no",
        "other": "no",
        "hebrew_text": "וְאַחֲרִיתֵךְ תֵּאָכֵל בָּאֵשׁ",
        "english_text": "your remnant shall be devoured by fire",
        "target": [
          "The surviving portion of the people/city",
          "Those remaining after initial judgment",
          "Historical-social domain"
        ],
        "vehicle": [
          "Food being eaten by a consumer (here: fire)",
          "Devouring consumption",
          "Bodily/natural-force domain"
        ],
        "ground": [
          "Fire consumes completely like an eater consumes food",
          "Total destruction and removal",
          "Annihilation domain"
        ],
        "posture": [
          "Stresses the thoroughness of the coming judgment",
          "Severe, uncompromising tone",
          "Prophetic-judgment stance"
        ],
        "explanation": "Fire is personified as an eater that 'devours' the remnant, picturing judgment as total consumption.",
        "confidence": 0.94
      }
    ]
  },
  {
    "verse": 26,
    "reference": "Ezekiel 23:26",
    "deliberation": "Stripping off clothing and taking jewelry is standard imagery of conquest and humiliation but can occur literally; here it is consistent with siege spoiling and need not be taken as an independent figurative expression beyond the ongoing allegory.",
    "instances": []
  },
  {
    "verse": 27,
    "reference": "Ezekiel 23:27",
    "deliberation": "God puts an end to 'your wantonness' and 'your whoring from the land of Egypt'; the whoring-from-Egypt phrase again uses prostitution language for Egypt-dependence and idolatry.",
    "instances": [
      {
        "figurative_language": "yes",
        "metaphor": "yes",
        "simile": "no",
        "personification": "yes",
        "idiom": "no",
        "hyperbole": "no",
        "metonymy": "no",
        "other": "no",
        "hebrew_text": "וְאֶת־זְנוּתֵךְ מֵאֶרֶץ מִצְרָיִם",
        "english_text": "and [I will put an end to] your whoring in the land of Egypt",
        "target": [
          "Egypt-related idolatry and alliances",
          "A specific pattern of covenant infidelity",
          "Theological-political domain"
        ],
        "vehicle": [
          "A woman’s acts of prostitution in a particular locale",
          "Sexual whoring tied to Egypt",
          "Sexual/locational domain"
        ],
        "ground": [
          "Local, characteristic pattern of illicit relations",
          "Distinctive foreign entanglements identified by place",
          "Historical-behavioral domain"
        ],
        "posture": [
          "God’s resolve to terminate that pattern of unfaithfulness",
          "Firm, corrective stance",
          "Theological-judgment posture"
        ],
        "explanation": "Whoring 'from Egypt' metaphorically denotes the fusion of Egypt-oriented politics and idolatry that God will end.",
        "confidence": 0.9
      }
    ]
  },
  {
    "verse": 28,
    "reference": "Ezekiel 23:28",
    "deliberation": "The phrase 'into the hand of those you hate' again uses 'hand' as metonymy for power/control; the rest is literal threat of being delivered to enemies.",
    "instances": [
      {
        "figurative_language": "yes",
        "metaphor": "no",
        "simile": "no",
        "personification": "no",
        "idiom": "yes",
        "hyperbole": "no",
        "metonymy": "yes",
        "other": "no",
        "hebrew_text": "נֹתְנָךְ בְּיַד אֲשֶׁר שָׂנֵאת",
        "english_text": "I am going to deliver you into the hands of those you hate",
        "target": [
          "Judah’s subjection to hated enemies",
          "Experience of enemy domination",
          "Political-military domain"
        ],
        "vehicle": [
          "Being placed into someone’s hand",
          "Control and power symbolized by the hand",
          "Bodily/action domain"
        ],
        "ground": [
          "The hand executes power and can grasp what it controls",
          "To be in another’s hand is to be under their authority",
          "Agency/control domain"
        ],
        "posture": [
          "Depicts this as a deliberate divine transfer of power",
          "Judicial, retributive tone",
          "Theological-judgment stance"
        ],
        "explanation": "The idiom 'into the hand' uses the hand metonymically for the enemies’ power over Judah.",
        "confidence": 0.92
      }
    ]
  },
  {
    "verse": 29,
    "reference": "Ezekiel 23:29",
    "deliberation": "Two figures: (1) 'all your labor' for accumulated wealth is metonymy, and (2) being left 'naked and bare' with 'nakedness of your whoredoms' exposed uses physical nakedness metaphorically for public shame and moral exposure.",
    "instances": [
      {
        "figurative_language": "yes",
        "metaphor": "no",
        "simile": "no",
        "personification": "no",
        "idiom": "no",
        "hyperbole": "no",
        "metonymy": "yes",
        "other": "no",
        "hebrew_text": "וְלָקְחוּ כָּל־יְגִיעֵךְ",
        "english_text": "and they shall take away all you have toiled for [lit. all your labor]",
        "target": [
          "Judah’s goods and wealth acquired by effort",
          "Material fruits of work",
          "Economic domain"
        ],
        "vehicle": [
          "Her 'labor' itself",
          "Work/effort standing for its results",
          "Activity-product domain"
        ],
        "ground": [
          "The results of labor are identified with the labor",
          "To lose the 'labor' is to lose what it produced",
          "Cause-effect domain"
        ],
        "posture": [
          "Highlights the total loss of her gains",
          "Warning about the futility of her efforts",
          "Prophetic-exhortative stance"
        ],
        "explanation": "The abstract 'labor' stands metonymically for the tangible goods produced by that labor.",
        "confidence": 0.88
      },
      {
        "figurative_language": "yes",
        "metaphor": "yes",
        "simile": "no",
        "personification": "no",
        "idiom": "yes",
        "hyperbole": "no",
        "metonymy": "no",
        "other": "no",
        "hebrew_text": "וְעֲזָבוּךְ עֵירֹם וְעֶרְיָה וְנִגְלָה עֶרְוַת זְנוּנַיִךְ",
        "english_text": "and leave you naked and bare; your naked licentiousness, wantonness, and whoredom will be exposed",
        "target": [
          "Judah’s public disgrace and exposure of sin",
          "Loss of honor, security, and concealment",
          "Social-moral domain"
        ],
        "vehicle": [
          "A woman stripped naked so that her sexual shame is seen",
          "Physical nakedness as shame",
          "Body/honor domain"
        ],
        "ground": [
          "Nakedness reveals what is meant to be concealed, bringing shame",
          "Hidden sins becoming visible to all",
          "Disclosure/shame domain"
        ],
        "posture": [
          "Intends to shame and unmask her conduct",
          "Severe, unveiling prophetic tone",
          "Judgmental-theological stance"
        ],
        "explanation": "Being left naked and having her 'whoredom' exposed metaphorically portrays the public revelation and disgrace of Judah’s sins.",
        "confidence": 0.95
      }
    ]
  },
  {
    "verse": 30,
    "reference": "Ezekiel 23:30",
    "deliberation": "Summarizes: these punishments happen 'for your whoring with the nations' and 'defiling yourself with their fetishes'; whoring with nations is the by-now familiar prostitution metaphor for international alliances and idolatry.",
    "instances": [
      {
        "figurative_language": "yes",
        "metaphor": "yes",
        "simile": "no",
        "personification": "yes",
        "idiom": "no",
        "hyperbole": "no",
        "metonymy": "no",
        "other": "no",
        "hebrew_text": "בִּזְנוֹתֵךְ אַחֲרֵי גוֹיִם",
        "english_text": "for your whoring with the nations",
        "target": [
          "Judah’s pursuit of foreign political-religious relationships",
          "Covenant-breaking internationalism",
          "Theological-political domain"
        ],
        "vehicle": [
          "A woman’s sexual whoring after many men",
          "Serial sexual promiscuity",
          "Sexual/relational domain"
        ],
        "ground": [
          "Chasing multiple forbidden partners instead of one lawful spouse",
          "Restless, indiscriminate seeking of outside attachments",
          "Loyalty/betrayal domain"
        ],
        "posture": [
          "Labels such foreign entanglements as inherently shameful betrayal",
          "Strongly condemnatory prophetic tone",
          "Judgmental stance"
        ],
        "explanation": "Her international dealings are cast as sexual whoring after nations, summarizing the chapter’s central metaphor.",
        "confidence": 0.96
      }
    ]
  },
  {
    "verse": 31,
    "reference": "Ezekiel 23:31",
    "deliberation": "Contains two distinct metaphors: (1) 'You walked in your sister’s path'—path for imitative conduct; (2) 'I will put her cup in your hand'—cup as share in judgment/fate.",
    "instances": [
      {
        "figurative_language": "yes",
        "metaphor": "yes",
        "simile": "no",
        "personification": "no",
        "idiom": "yes",
        "hyperbole": "no",
        "metonymy": "no",
        "other": "no",
        "hebrew_text": "בְּדֶרֶךְ אֲחוֹתֵךְ הָלָכְתְּ",
        "english_text": "You walked in your sister’s path",
        "target": [
          "Judah’s imitation of Samaria’s behavior",
          "Adoption of the same sinful patterns",
          "Ethical-historical domain"
        ],
        "vehicle": [
          "Walking in another’s road or path",
          "Following someone’s literal route",
          "Spatial/motion domain"
        ],
        "ground": [
          "Traveling the same path leads to the same destination",
          "Imitating another’s actions leads to similar outcomes",
          "Causality/imitation domain"
        ],
        "posture": [
          "Highlights culpable imitation of a known negative example",
          "Didactic and accusatory tone",
          "Prophetic-warning stance"
        ],
        "explanation": "Judah’s duplicating Samaria’s sins is depicted as walking in her sister’s path.",
        "confidence": 0.95
      },
      {
        "figurative_language": "yes",
        "metaphor": "yes",
        "simile": "no",
        "personification": "no",
        "idiom": "yes",
        "hyperbole": "no",
        "metonymy": "no",
        "other": "no",
        "hebrew_text": "וְנָתַתִּי כּוֹסָהּ בְּיָדֵךְ",
        "english_text": "therefore I will put her cup into your hand",
        "target": [
          "The experience of judgment that befell Samaria, now for Judah",
          "Portion of suffering/punishment",
          "Theological-judicial domain"
        ],
        "vehicle": [
          "A cup one is given to drink",
          "Assigned drink/portion",
          "Embodied/material domain"
        ],
        "ground": [
          "The cup handed to you is what you must drink",
          "Receiving the same allotted fate as another",
          "Portion/destiny domain"
        ],
        "posture": [
          "Stresses inevitable sharing in Samaria’s fate",
          "Solemn prophetic warning",
          "Judgmental-theological stance"
        ],
        "explanation": "Samaria’s fate is pictured as a 'cup' of judgment that Judah will also be given to drink.",
        "confidence": 0.97
      }
    ]
  },
  {
    "verse": 32,
    "reference": "Ezekiel 23:32",
    "deliberation": "Develops the 'cup' metaphor further: a deep and wide cup that brings derision and scorn, clearly symbolizing a large measure of suffering and humiliation.",
    "instances": [
      {
        "figurative_language": "yes",
        "metaphor": "yes",
        "simile": "no",
        "personification": "no",
        "idiom": "yes",
        "hyperbole": "yes",
        "metonymy": "no",
        "other": "no",
        "hebrew_text": "כּוֹס אֲחוֹתֵךְ תִּשְׁתִּי הָעֲמֻקָּה וְהָרְחָבָה",
        "english_text": "You shall drink of your sister’s cup, so deep and wide",
        "target": [
          "The severity and extent of Judah’s coming judgment",
          "A large allotted portion of suffering",
          "Theological-judicial domain"
        ],
        "vehicle": [
          "A very deep and wide drinking cup",
          "Large vessel filled with intoxicating drink",
          "Material/consumption domain"
        ],
        "ground": [
          "A bigger cup holds more to drink, implying more to endure",
          "Judgment conceptualized as a quantity one must imbibe",
          "Measure/experience domain"
        ],
        "posture": [
          "Emphasizes the overwhelming nature of the judgment",
          "Blends warning with a note of grim irony (it will cause derision)",
          "Prophetic-judgment stance"
        ],
        "explanation": "The deep and wide cup symbolizes an enormous measure of judgment and disgrace that Judah must 'drink' like Samaria.",
        "confidence": 0.96
      }
    ]
  },
  {
    "verse": 33,
    "reference": "Ezekiel 23:33",
    "deliberation": "Continues the cup image: filled with drunkenness and woe; 'cup of desolation and horror' equates the drink with catastrophic experiences.",
    "instances": [
      {
        "figurative_language": "yes",
        "metaphor": "yes",
        "simile": "no",
        "personification": "no",
        "idiom": "yes",
        "hyperbole": "no",
        "metonymy": "no",
        "other": "no",
        "hebrew_text": "שִׁכָּרוֹן וְיָגוֹן תִּמָּלֵאִי כּוֹס שַׁמָּה וּשְׁמָמָה כּוֹס אֲחוֹתֵךְ שֹׁמְרוֹן",
        "english_text": "You shall be filled with drunkenness and woe. The cup of desolation and horror, the cup of your sister Samaria—",
        "target": [
          "Judah’s inner turmoil and devastation under judgment",
          "Emotional and material ruin",
          "Psychological-historical domain"
        ],
        "vehicle": [
          "Drunkenness from a cup filled with desolation",
          "Intoxication causing staggering and misery",
          "Embodied/experiential domain"
        ],
        "ground": [
          "Intoxication leads to confusion, loss of control, and pain",
          "Overwhelming woe is like being drunk on a bitter draught",
          "Disorientation/suffering domain"
        ],
        "posture": [
          "Stresses the disorienting, painful nature of the coming disaster",
          "Grimly descriptive prophetic tone",
          "Judgmental-theological stance"
        ],
        "explanation": "The 'cup of desolation and horror' and resulting drunkenness metaphorically describe Judah’s overwhelming, disorienting experience of judgment.",
        "confidence": 0.95
      }
    ]
  },
  {
    "verse": 34,
    "reference": "Ezekiel 23:34",
    "deliberation": "Extends the cup-metaphor to its extreme: drinking, draining, and gnawing its shards is vivid hyperbole for exhausting the judgment; tearing the breasts reflects grief/shame within the prostitution imagery.",
    "instances": [
      {
        "figurative_language": "yes",
        "metaphor": "yes",
        "simile": "no",
        "personification": "no",
        "idiom": "yes",
        "hyperbole": "yes",
        "metonymy": "no",
        "other": "no",
        "hebrew_text": "וְשָׁתִית אוֹתָהּ וּמָצִית וְאֶת־חֲרָשֶׂיהָ תְּגָרֵמִי",
        "english_text": "You shall drink it and drain it, and gnaw its shards",
        "target": [
          "Complete undergoing of the decreed judgment",
          "Total experience of punishment with nothing held back",
          "Theological-judicial domain"
        ],
        "vehicle": [
          "A drinker who not only drains a cup but chews its fragments",
          "Extreme, painful consumption",
          "Embodied/hyperbolic domain"
        ],
        "ground": [
          "Gnawing shards is excessive and self-injuring, signaling extremity",
          "No part of the 'cup' (judgment) left untasted",
          "Totality/intensity domain"
        ],
        "posture": [
          "Emphasizes the exhaustive, even self-destructive extent of judgment",
          "Highly dramatic prophetic rhetoric",
          "Judgmental-theological stance"
        ],
        "explanation": "Drinking, draining, and gnawing the cup’s shards hyperbolically portray Judah’s full, painful endurance of the judgment allotted to her.",
        "confidence": 0.95
      }
    ]
  },
  {
    "verse": 35,
    "reference": "Ezekiel 23:35",
    "deliberation": "Two idiomatic metaphors: (1) 'you have cast Me behind your back'—treating God like something discarded; (2) 'bear your lewdness and whoredoms'—to carry/answer for one’s guilt.",
    "instances": [
      {
        "figurative_language": "yes",
        "metaphor": "yes",
        "simile": "no",
        "personification": "no",
        "idiom": "yes",
        "hyperbole": "no",
        "metonymy": "no",
        "other": "no",
        "hebrew_text": "וַתַּשְׁלִיכִי אוֹתִי אַחֲרֵי גַוֵּךְ",
        "english_text": "you have cast Me behind your back",
        "target": [
          "Israel/Judah’s disregard and rejection of God",
          "Despising God’s presence and claims",
          "Theological-relational domain"
        ],
        "vehicle": [
          "Throwing something behind one’s back",
          "Discarding/ignoring an object",
          "Spatial/gestural domain"
        ],
        "ground": [
          "What is behind the back is out of sight and concern",
          "Casting something away expresses rejection",
          "Attention/value domain"
        ],
        "posture": [
          "Presents their attitude as willful and contemptuous",
          "Strong divine reproach",
          "Judgmental-theological stance"
        ],
        "explanation": "Treating God as something thrown behind one’s back metaphorically depicts deliberate rejection and disregard.",
        "confidence": 0.97
      },
      {
        "figurative_language": "yes",
        "metaphor": "yes",
        "simile": "no",
        "personification": "no",
        "idiom": "yes",
        "hyperbole": "no",
        "metonymy": "no",
        "other": "no",
        "hebrew_text": "שְׂאִי זִמָּתֵךְ וְאֶת־תַּזְנוּתָיִךְ",
        "english_text": "you in turn must suffer [lit. bear] for your wanton whoring",
        "target": [
          "The consequences and guilt of her immoral behavior",
          "Punishment/responsibility for sin",
          "Ethical-judicial domain"
        ],
        "vehicle": [
          "Carrying a burden",
          "Bearing a weight",
          "Physical/load domain"
        ],
        "ground": [
          "Guilt and its consequences weigh upon a person",
          "To 'bear' sin is to carry its burden and penalty",
          "Burden/responsibility domain"
        ],
        "posture": [
          "Asserts that she must finally carry what she has done",
          "Retributive, balanced justice tone",
          "Theological-judicial stance"
        ],
        "explanation": "To 'bear' her lewdness and whoredoms metaphorically means to carry and experience the penalty for them.",
        "confidence": 0.94
      }
    ]
  },
  {
    "verse": 36,
    "reference": "Ezekiel 23:36",
    "deliberation": "Legal language about judging and declaring abominations; here it is straightforward instruction to bring charges, consistent with prophetic courtroom imagery but not a distinct new figure in this verse.",
    "instances": []
  },
  {
    "verse": 37,
    "reference": "Ezekiel 23:37",
    "deliberation": "Two key figures: (1) 'blood is on their hands'—metaphor/idiom for guilt in murder; (2) 'committed adultery with their fetishes'—continuation of adultery metaphor for idolatry.",
    "instances": [
      {
        "figurative_language": "yes",
        "metaphor": "yes",
        "simile": "no",
        "personification": "no",
        "idiom": "yes",
        "hyperbole": "no",
        "metonymy": "no",
        "other": "no",
        "hebrew_text": "דָּם בִּידֵיהֶן",
        "english_text": "blood is on their hands",
        "target": [
          "Their culpability for violence and child sacrifice",
          "Moral-legal guilt for bloodshed",
          "Ethical-judicial domain"
        ],
        "vehicle": [
          "Literal blood staining a person’s hands",
          "Physical trace of killing",
          "Bodily/forensic domain"
        ],
        "ground": [
          "Blood on hands evidences killing and responsibility",
          "Visible sign of hidden crime",
          "Evidence/guilt domain"
        ],
        "posture": [
          "Accuses them as unmistakably guilty",
          "Forensic, prosecutorial tone",
          "Prophetic-courtroom stance"
        ],
        "explanation": "The idiom 'blood on their hands' metaphorically depicts their clear guilt in shedding innocent blood.",
        "confidence": 0.97
      },
      {
        "figurative_language": "yes",
        "metaphor": "yes",
        "simile": "no",
        "personification": "yes",
        "idiom": "no",
        "hyperbole": "no",
        "metonymy": "no",
        "other": "no",
        "hebrew_text": "אֶת־גִּלּוּלֵיהֶן נִאֵפוּ",
        "english_text": "they have committed adultery with their fetishes",
        "target": [
          "Their idolatrous worship of carved images",
          "Breached covenant loyalty to God",
          "Theological-cultic domain"
        ],
        "vehicle": [
          "A married woman committing adultery with other men",
          "Sexual betrayal of the marriage bond",
          "Sexual/marital domain"
        ],
        "ground": [
          "Exclusive loyalty owed to one partner is given to others",
          "Intimate union with rivals to the rightful spouse",
          "Loyalty/betrayal domain"
        ],
        "posture": [
          "Frames idolatry as deeply personal betrayal of God",
          "Emotionally charged prophetic accusation",
          "Judgmental-theological stance"
        ],
        "explanation": "Calling idolatry 'adultery with fetishes' personifies the idols as illicit lovers and depicts worship of them as marital infidelity to God.",
        "confidence": 0.96
      }
    ]
  },
  {
    "verse": 38,
    "reference": "Ezekiel 23:38",
    "deliberation": "Describes defiling the sanctuary and profaning Sabbaths in straightforward cultic terms; while 'defile' and 'profane' draw on purity metaphors, here they function as standard covenant-legal vocabulary.",
    "instances": []
  },
  {
    "verse": 39,
    "reference": "Ezekiel 23:39",
    "deliberation": "States that they did these acts 'in My house'—a regular metaphor/metonymy for the temple as God’s house, i.e., dwelling place.",
    "instances": [
      {
        "figurative_language": "yes",
        "metaphor": "yes",
        "simile": "no",
        "personification": "no",
        "idiom": "no",
        "hyperbole": "no",
        "metonymy": "yes",
        "other": "no",
        "hebrew_text": "בְּתוֹךְ בֵּיתִי",
        "english_text": "in My House",
        "target": [
          "The Jerusalem temple as locus of divine presence",
          "Cultic institution and its space",
          "Religious-institutional domain"
        ],
        "vehicle": [
          "A personal 'house' belonging to a master",
          "Domestic dwelling",
          "Family/space domain"
        ],
        "ground": [
          "A house is where someone dwells and is honored",
          "Desecration there is intimate affront",
          "Honor/space domain"
        ],
        "posture": [
          "Highlights the intimacy and seriousness of the profanation",
          "Personalizes the offense against God",
          "Theological-relational stance"
        ],
        "explanation": "Calling the temple 'My house' metaphorically presents it as God’s own dwelling, intensifying the offense of their actions there.",
        "confidence": 0.93
      }
    ]
  },
  {
    "verse": 40,
    "reference": "Ezekiel 23:40",
    "deliberation": "Describes sending for men from afar and beautifying herself. Within the allegory this grooming is metaphor for political courting and seductive diplomacy.",
    "instances": [
      {
        "figurative_language": "yes",
        "metaphor": "yes",
        "simile": "no",
        "personification": "yes",
        "idiom": "no",
        "hyperbole": "no",
        "metonymy": "no",
        "other": "no",
        "hebrew_text": "רָחַצְתְּ כָּחַלְתְּ עֵינַיִךְ וְעָדִית עֶדִי",
        "english_text": "you bathed, painted your eyes, and donned your finery",
        "target": [
          "Judah’s diplomatic and cultic preparation to receive foreign powers",
          "Calculated courting of distant nations",
          "Political-religious domain"
        ],
        "vehicle": [
          "A woman washing, adorning, and making herself up for lovers",
          "Seductive beautification",
          "Sexual/social domain"
        ],
        "ground": [
          "Self-adornment to attract desired partners",
          "Effort to appear desirable and sophisticated",
          "Presentation/attraction domain"
        ],
        "posture": [
          "Depicts such diplomatic courting as shameless seduction",
          "Critical, morally charged tone",
          "Prophetic-judgment stance"
        ],
        "explanation": "Her political and cultic courting of foreign men is figured as a woman bathing, painting her eyes, and adorning herself to seduce lovers from afar.",
        "confidence": 0.95
      }
    ]
  },
  {
    "verse": 41,
    "reference": "Ezekiel 23:41",
    "deliberation": "The 'grand couch' and 'set table' with 'My incense and My oil' continue the image of a lavish prostitute’s setting, standing for idolatrous feasts using God’s resources.",
    "instances": [
      {
        "figurative_language": "yes",
        "metaphor": "yes",
        "simile": "no",
        "personification": "yes",
        "idiom": "no",
        "hyperbole": "no",
        "metonymy": "yes",
        "other": "no",
        "hebrew_text": "וְיָשַׁבְתְּ עַל־מִטָּה כְּבוּדָּה וְשֻׁלְחָן עָרוּךְ לְפָנֶיהָ וּקְטׇרְתִּי וְשַׁמְנִי שַׂמְתְּ עָלֶיהָ",
        "english_text": "and you sat on a grand couch with a set table in front of it—and it was My incense and My oil you laid upon it.",
        "target": [
          "Idolatrous banquets and cultic practices supported by YHWH’s gifts",
          "Misuse of divine resources in foreign worship",
          "Theological-cultic domain"
        ],
        "vehicle": [
          "A richly adorned courtesan reclining with a prepared table scented with incense and oil",
          "Luxurious setting of a high-status prostitute",
          "Social/ritual domain"
        ],
        "ground": [
          "Lavish environment implies costly, intimate, and dishonorable liaisons",
          "Goods of the rightful lord used in dishonorable feasts",
          "Honor/resources domain"
        ],
        "posture": [
          "Accuses her of turning God’s own gifts into tools of infidelity",
          "Indignant and ironic prophetic tone",
          "Judgmental-theological stance"
        ],
        "explanation": "The luxurious couch and table with God’s incense and oil represent idolatrous feasting and cultic prostitution financed by YHWH’s blessings.",
        "confidence": 0.94
      }
    ]
  },
  {
    "verse": 42,
    "reference": "Ezekiel 23:42",
    "deliberation": "Describes a carefree noisy crowd and men from the desert putting bracelets and crowns on the women. These are vivid narrative details of the allegory, not additional discrete figurative constructions beyond the ongoing prostitution imagery.",
    "instances": []
  },
  {
    "verse": 43,
    "reference": "Ezekiel 23:43",
    "deliberation": "God speaks about 'the one worn out with adulteries' and her ongoing fornications—again treating the city as a sexually used-up prostitute continuing in whoredom.",
    "instances": [
      {
        "figurative_language": "yes",
        "metaphor": "yes",
        "simile": "no",
        "personification": "yes",
        "idiom": "no",
        "hyperbole": "yes",
        "metonymy": "no",
        "other": "no",
        "hebrew_text": "לַבָּלָה נִאוּפִים עַתָּה יִזְנוּ תַזְנוּתֶהָ",
        "english_text": "To [the woman] worn out with adultery, ‘Now they will go on with her fornications’",
        "target": [
          "Judah’s long history of repeated unfaithfulness",
          "Exhausted yet ongoing pattern of sin",
          "Theological-historical domain"
        ],
        "vehicle": [
          "A woman worn out by many adulteries yet continuing fornication",
          "Sexually overused but still active prostitute",
          "Sexual/physical domain"
        ],
        "ground": [
          "Exhaustion from repeated acts implies long-standing, intensive practice",
          "Persistence in corruption despite being 'used up'",
          "Moral-intransigence domain"
        ],
        "posture": [
          "Conveys disgust and incredulity at unrelenting sin",
          "Ironic, exasperated divine tone",
          "Prophetic-judgment stance"
        ],
        "explanation": "Calling her 'worn out with adulteries' yet still whoring hyperbolically portrays the long, exhausting history and stubborn continuation of Judah’s infidelity.",
        "confidence": 0.92
      }
    ]
  },
  {
    "verse": 44,
    "reference": "Ezekiel 23:44",
    "deliberation": "Contains an explicit simile: 'as one goes to a prostitute, so they went to Oholah and Oholibah', reinforcing the cities’ identity as wanton women.",
    "instances": [
      {
        "figurative_language": "yes",
        "metaphor": "no",
        "simile": "yes",
        "personification": "yes",
        "idiom": "no",
        "hyperbole": "no",
        "metonymy": "no",
        "other": "no",
        "hebrew_text": "כְּבֹא אֶל־אִשָּׁה זוֹנָה כֵּן בָּאוּ אֶל־אׇהֳלָה וְאֶל־אׇהֳלִיבָה",
        "english_text": "They would go to her as one goes to a prostitute; that is how they went to Oholah and Oholibah",
        "target": [
          "The nations’ interactions with Samaria and Jerusalem",
          "Sexualized, exploitative foreign relations",
          "Political-relational domain"
        ],
        "vehicle": [
          "Men going to a prostitute",
          "Commercial sexual encounter",
          "Sexual/social domain"
        ],
        "ground": [
          "Transactional, morally compromised contact",
          "Lack of covenantal commitment; use for pleasure or gain",
          "Use/abuse domain"
        ],
        "posture": [
          "Depicts the cities as degraded to the level of common prostitutes",
          "Strongly disparaging tone",
          "Prophetic-judgment stance"
        ],
        "explanation": "The simile explicitly compares how the nations approached Oholah and Oholibah to how one goes to a prostitute, underlining their wantonness.",
        "confidence": 0.97
      }
    ]
  },
  {
    "verse": 45,
    "reference": "Ezekiel 23:45",
    "deliberation": "Again uses the idiom 'blood on their hands' for guilt, alongside literal legal language about judgments for adulteresses and bloodshedders.",
    "instances": [
      {
        "figurative_language": "yes",
        "metaphor": "yes",
        "simile": "no",
        "personification": "no",
        "idiom": "yes",
        "hyperbole": "no",
        "metonymy": "no",
        "other": "no",
        "hebrew_text": "וְדָם בִּידֵיהֶן",
        "english_text": "and blood is on their hands",
        "target": [
          "Their responsibility for violent crimes",
          "Legal and moral culpability",
          "Ethical-judicial domain"
        ],
        "vehicle": [
          "Blood literally on one’s hands",
          "Visible stain of killing",
          "Bodily/forensic domain"
        ],
        "ground": [
          "Blood on hands signals direct involvement in killing",
          "Indelible mark of guilt",
          "Evidence/guilt domain"
        ],
        "posture": [
          "Affirms that righteous judges will rightly condemn them",
          "Forensic, condemnatory tone",
          "Prophetic-courtroom stance"
        ],
        "explanation": "The repeated idiom conveys that they bear unmistakable guilt for bloodshed.",
        "confidence": 0.96
      }
    ]
  },
  {
    "verse": 46,
    "reference": "Ezekiel 23:46",
    "deliberation": "Speaks of summoning an assembly and making them 'an object of horror and plunder'; these are strong terms but fall within literal judicial/military language of public punishment.",
    "instances": []
  },
  {
    "verse": 47,
    "reference": "Ezekiel 23:47",
    "deliberation": "Describes stoning, cutting down with swords, killing children, and burning houses in concrete judicial-conquest terms; no distinct figurative construction beyond the severe imagery itself.",
    "instances": []
  },
  {
    "verse": 48,
    "reference": "Ezekiel 23:48",
    "deliberation": "States 'I will put an end to wantonness in the land'; 'land' stands for its inhabitants, a mild metonymy, but otherwise the language is straightforward policy of eradicating a practice.",
    "instances": []
  },
  {
    "verse": 49,
    "reference": "Ezekiel 23:49",
    "deliberation": "Uses 'they will put your wantonness upon you' and 'you shall bear the penalty for your sinful idolatry'; the key figure is bearing sins as carrying a burden of guilt.",
    "instances": [
      {
        "figurative_language": "yes",
        "metaphor": "yes",
        "simile": "no",
        "personification": "no",
        "idiom": "yes",
        "hyperbole": "no",
        "metonymy": "no",
        "other": "no",
        "hebrew_text": "וַחֲטָאֵי גִלּוּלֵיכֶן תִּשֶּׂאינָה",
        "english_text": "and you shall suffer the penalty for your sinful idolatry [lit. bear the sins of your fetishes]",
        "target": [
          "The consequences and liability for their idolatry",
          "Enduring punishment for sin",
          "Ethical-judicial domain"
        ],
        "vehicle": [
          "Bearing/carrying a load",
          "A weight resting on someone",
          "Physical/burden domain"
        ],
        "ground": [
          "Guilt and its consequences rest heavily on the sinner",
          "To bear a load is to endure its strain and weight",
          "Burden/responsibility domain"
        ],
        "posture": [
          "Insists that they will personally carry the results of their actions",
          "Serious, admonitory prophetic tone",
          "Theological-judicial stance"
        ],
        "explanation": "To 'bear' the sins of their idols metaphorically depicts them carrying and enduring the penalty of their idolatry as a heavy burden.",
        "confidence": 0.94
      }
    ]
  }
]